gevent_breaker/__init__.py
gevent_breaker/breaker.py
gevent_breaker-1.0.0.dist-info/DESCRIPTION.rst
gevent_breaker-1.0.0.dist-info/METADATA
gevent_breaker-1.0.0.dist-info/RECORD
gevent_breaker-1.0.0.dist-info/WHEEL
gevent_breaker-1.0.0.dist-info/metadata.json
gevent_breaker-1.0.0.dist-info/top_level.txt
test/__init__.py
test/test_breaker.py
