Metadata-Version: 1.1
Name: gevent-breaker
Version: 1.0.0
Summary: Circuitbreaker pattern for gevent apps
Home-page: http://github.com/daroot/gevent-breaker
Author: Dan Root
Author-email: rootdan+pypi@gmail.com
License: WTFPL
Keywords: pytest,consul
Platform: any
Classifier: Development Status :: 3 - Alpha
Classifier: Intended Audience :: Developers
Classifier: License :: Freely Distributable
Classifier: Operating System :: OS Independent
Classifier: Programming Language :: Python
Classifier: Programming Language :: Python :: 2.7
Classifier: Programming Language :: Python :: 3.3
Classifier: Programming Language :: Python :: 3.4
Classifier: Programming Language :: Python :: 3.5
